htmlentities/__init__.py
tests/__init__.py
tests/test_decoding.py
tests/test_encoding.py
htmlentities-0.3.0.dist-info/METADATA
htmlentities-0.3.0.dist-info/WHEEL
htmlentities-0.3.0.dist-info/top_level.txt
htmlentities-0.3.0.dist-info/RECORD
