Metadata-Version: 2.1
Name: htmlentities
Version: 0.3.0
Summary: HTML Entities for Python
Home-page: UNKNOWN
Author: CobraTeam
Author-email: andrewsmedina@gmail.com
License: UNKNOWN
Platform: UNKNOWN
